{
    "schema": {
        "picto_inner_diameter": {
            "type": "double",
            "default": 2.0,
            "unit": "mm"
        },
        "picto_outer_diameter": {
            "type": "double",
            "default": 4.0,
            "unit": "mm"
        },
        "picto_inner_length": {
            "type": "double",
            "default": 4.0,
            "unit": "mm"
        },
        "picto_outer_length": {
            "type": "double",
            "default": 4.0,
            "unit": "mm"
        },
        "bin_span": {
            "type": "double",
            "default": 1.0,
            "unit": "ggu"
        },
        "label_text": {
            "type": "string",
            "default": "[label_text]",
            "unit": "null"
        }
    }
}